get_snirh/__init__.py
get_snirh/client.py
get_snirh/constants.py
get_snirh/data.py
get_snirh/exceptions.py
get_snirh/stations.py
get_snirh/utils.py
get_snirh/data/rede_Meteorologica.csv
get_snirh/data/rede_Piezometria.csv
get_snirh/data/rede_Qualidadeaguassubterraneas.csv
get_snirh/data/rede_seleccao_Hidrometrica.csv
get_snirh/data/rede_seleccao_HidrometricaAlgarve.csv
get_snirh/data/rede_seleccao_Qualidade.csv
get_snirh/data/station_list_meteo.csv
get_snirh/data/station_list_piez.csv
get_snirh/data/station_list_quality.csv
get_snirh/data/station_list_sw_hidrometrica.csv
get_snirh/data/station_list_sw_quality.csv
get_snirh-0.1.1.dist-info/licenses/LICENSE
get_snirh-0.1.1.dist-info/METADATA
get_snirh-0.1.1.dist-info/WHEEL
get_snirh-0.1.1.dist-info/top_level.txt
get_snirh-0.1.1.dist-info/RECORD
