Metadata-Version: 2.4
Name: get-snirh
Version: 0.1.1
Summary: A Python package to automate downloading water resource data from SNIRH
Author: Rui Hugman, Luis Costa
Project-URL: Homepage, https://github.com/rhugman/get-snirh
Project-URL: Repository, https://github.com/rhugman/get-snirh
Project-URL: Bug Tracker, https://github.com/rhugman/get-snirh/issues
Keywords: snirh,water,hydrology,portugal,environment,data
Classifier: Programming Language :: Python :: 3
Classifier: License :: OSI Approved :: GNU General Public License v3 (GPLv3)
Classifier: Operating System :: OS Independent
Classifier: Development Status :: 3 - Alpha
Classifier: Intended Audience :: Science/Research
Classifier: Topic :: Scientific/Engineering :: Hydrology
Requires-Python: >=3.8
License-File: LICENSE
Requires-Dist: pandas>=1.0.0
Requires-Dist: requests>=2.25.0
Dynamic: license-file
